[
    {
        "name": "Farewell - Power Source Key 1",
        "visibility_rules": [
            "include_farewell"
        ],
        "sections": [
            {
                "access_rules": []
            }
        ],
        "map_locations": [
            {
                "map": "9a-3",
                "x": 1967,
                "y": 1607,
                "shape": "trapezoid"
            }
        ]
    },
    {
        "name": "Farewell - Power Source Key 2",
        "visibility_rules": [
            "include_farewell"
        ],
        "sections": [
            {
                "access_rules": []
            }
        ],
        "map_locations": [
            {
                "map": "9a-3",
                "x": 2623,
                "y": 615,
                "shape": "trapezoid"
            }
        ]
    },
    {
        "name": "Farewell - Power Source Key 3",
        "visibility_rules": [
            "include_farewell"
        ],
        "sections": [
            {
                "access_rules": []
            }
        ],
        "map_locations": [
            {
                "map": "9a-3",
                "x": 4367,
                "y": 1711,
                "shape": "trapezoid"
            }
        ]
    },
    {
        "name": "Farewell - Power Source Key 4",
        "visibility_rules": [
            "include_farewell"
        ],
        "sections": [
            {
                "access_rules": []
            }
        ],
        "map_locations": [
            {
                "map": "9a-3",
                "x": 4271,
                "y": 1335,
                "shape": "trapezoid"
            }
        ]
    },
    {
        "name": "Farewell - Power Source Key 5",
        "visibility_rules": [
            "include_farewell"
        ],
        "sections": [
            {
                "access_rules": []
            }
        ],
        "map_locations": [
            {
                "map": "9a-3",
                "x": 3775,
                "y": 1023,
                "shape": "trapezoid"
            }
        ]
    }
]