{
    "tracker_collectables": {
        "type": "array",
        "orientation": "horizontal",
        "content": [
            {
                "type": "itemgrid",
                "h_alignment": "left",
                "item_margin": "2,2",
                "item_size": "5",
                "rows": [
                    [
                        "strawberry"
                    ],
                    [
                        "raspberry"
                    ]
                ]
            }
        ]
    },
    "tracker_unlocks": {
        "type": "array",
        "orientation": "horizontal",
        "content": [
            {
                "type": "itemgrid",
                "h_alignment": "left",
                "item_margin": "2,2",
                "item_size": "3",
                "rows": [
                    [ "forsakencitya-icon", "oldsitea-icon", "celestialresorta-icon", "goldenridgea-icon", "mirrortemplea-icon", "reflectiona-icon", "thesummita-icon", "corea-icon", "farewell-icon", "" ],
                    [ "springs", "dreamblocks", "sinkingplatforms", "blueclouds", "swapblocks", "feathers", "", "fireandiceballs", "doubledashrefills", "pinkcassetteblocks" ],
                    [ "trafficblocks", "coins", "movingplatforms", "pinkclouds", "redboosters", "bumpers", "", "coreblocks", "pufferfish", "bluecassetteblocks" ],
                    [ "dashrefills", "strawberryseeds", "", "blueboosters", "dashswitches", "kevins", "", "coretoggles", "jellyfish", "yellowcassetteblocks" ],
                    [ "", "", "", "moveblocks", "seekers", "badelineboosters", "", "", "breakerboxes", "greencassetteblocks" ],
                    [ "", "", "", "whiteblock", "theocrystal", "", "", "", "bird", "" ],
                    [ "", "", "", "", "torch", "", "", "", "", "" ]
                ]
            }
        ]
    },
    "tracker_keys_gems": {
        "type": "array",
        "orientation": "horizontal",
        "content": [
            {
                "type": "itemgrid",
                "h_alignment": "left",
                "item_margin": "2,2",
                "item_size": "3",
                "rows": [
                    [ "celestialresorta-icon", "mirrortemplea-icon", "thesummita-icon", "farewell-icon" ],
                    [ "celestialresorta-frontdoorkey", "mirrortemplea-entrancekey", "thesummita-2500mkey", "farewell-powersourcekey1" ],
                    [ "celestialresorta-hallwaykey1", "mirrortemplea-depthskey", "thesummita-gem1", "farewell-powersourcekey2" ],
                    [ "celestialresorta-hallwaykey2", "mirrortemplea-searchkey1", "thesummita-gem2", "farewell-powersourcekey3" ],
                    [ "celestialresorta-hugemesskey", "mirrortemplea-searchkey2", "thesummita-gem3", "farewell-powersourcekey4" ],
                    [ "celestialresorta-presidentialsuitekey", "mirrortemplea-searchkey3", "thesummita-gem4", "farewell-powersourcekey5" ],
                    [ "", "mirrortempleb-centralchamberkey1", "thesummita-gem5", "" ],
                    [ "", "mirrortempleb-centralchamberkey2", "thesummita-gem6", "" ]
                ]
            }
        ]
    },
    "tracker_checkpoints": {
        "type": "array",
        "orientation": "horizontal",
        "content": [
            {
                "type": "itemgrid",
                "h_alignment": "left",
                "item_margin": "2,2",
                "item_size": "2",
                "rows": [
                    [ "forsakencitya-icon", "forsakencityb-icon", "oldsitea-icon", "oldsiteb-icon", "celestialresorta-icon", "celestialresortb-icon", "goldenridgea-icon", "goldenridgeb-icon", "mirrortemplea-icon", "mirrortempleb-icon", "reflectiona-icon", "reflectionb-icon", "thesummita-icon", "thesummitb-icon", "corea-icon", "coreb-icon", "farewell-icon" ],
                    [ "forsakencitya-crossing", "forsakencityb-contraption", "oldsitea-intervention", "oldsiteb-combinationlock", "celestialresorta-hugemess", "celestialresortb-staffquarters", "goldenridgea-shrine", "goldenridgeb-steppingstones", "mirrortemplea-depths", "mirrortempleb-centralchamber", "reflectiona-hollows", "reflectionb-reflection", "thesummita-500m", "thesummitb-500m", "corea-intothecore", "coreb-intothecore", "farewell-singular" ],
                    [ "forsakencitya-chasm", "forsakencityb-scrappit", "oldsitea-awake", "oldsiteb-dreamaltar", "celestialresorta-elevatorshaft", "celestialresortb-library", "goldenridgea-oldtrail", "goldenridgeb-gustycanyon", "mirrortemplea-unravelling", "mirrortempleb-throughthemirror", "reflectiona-reflection", "reflectionb-rockbottom", "thesummita-1000m", "thesummitb-1000m", "corea-hotandcold", "coreb-burningorfreezing", "farewell-powersource" ],
                    [ "", "", "", "", "celestialresorta-presidentialsuite", "celestialresortb-rooftop", "goldenridgea-cliffface", "goldenridgeb-eyeofthestorm", "mirrortemplea-search", "mirrortempleb-mixmaster", "reflectiona-rockbottom", "reflectionb-reprieve", "thesummita-1500m", "thesummitb-1500m", "corea-heartofthemountain", "coreb-heartbeat", "farewell-remembered" ],
                    [ "", "", "", "", "", "", "", "", "mirrortemplea-rescue", "", "reflectiona-resolution", "", "thesummita-2000m", "thesummitb-2000m", "", "", "farewell-eventhorizon" ],
                    [ "", "", "", "", "", "", "", "", "", "", "", "", "thesummita-2500m", "thesummitb-2500m", "", "", "farewell-determination" ],
                    [ "", "", "", "", "", "", "", "", "", "", "", "", "thesummita-3000m", "thesummitb-3000m", "", "", "farewell-stubbornness" ],
                    [ "", "", "", "", "", "", "", "", "", "", "", "", "", "", "", "", "farewell-reconciliation" ],
                    [ "", "", "", "", "", "", "", "", "", "", "", "", "", "", "", "", "farewell-farewell" ]
                ]
            }
        ]
    },
    "tracker_settings": {
        "type": "array",
        "orientation": "horizontal",
        "content": [
            {
                "type": "itemgrid",
                "h_alignment": "left",
                "item_margin": "2,2",
                "item_size": "5",
                "rows": [
                    [
                        "strawberries_required",
                        "goal_area",
                        "require_cassettes",
                        "difficulty",
                        "lock_goal_area"
                    ],
                    [
                        "include_b_sides",
                        "include_c_sides",
                        "include_core",
                        "include_farewell",
                        "include_goldens"
                    ],
                    [
                        "carsanity",
                        "roomsanity",
                        "keysanity",
                        "gemsanity",
                        "binosanity",
                        "checkpointsanity"
                    ]
                ]
            }
        ]
    }
}
