{
    "4a": {
        "type": "tabbed",
        "tabs": [
            {
                "title": "4A - Start",
                "content": {
                    "type": "map",
                    "maps": [
                        "4a-1"
                    ]
                }
            },
            {
                "title": "4A - Shrine",
                "content": {
                    "type": "map",
                    "maps": [
                        "4a-2"
                    ]
                }
            },
            {
                "title": "4A - Old Trail",
                "content": {
                    "type": "map",
                    "maps": [
                        "4a-3"
                    ]
                }
            },
            {
                "title": "4A - Cliff Face",
                "content": {
                    "type": "map",
                    "maps": [
                        "4a-4"
                    ]
                }
            }
        ]
    }
}